is_lib-1.0.0.dist-info/licenses/LICENSE
moja_biblioteka/__init__.py
moja_biblioteka/moduł1.py
is_lib-1.0.0.dist-info/METADATA
is_lib-1.0.0.dist-info/WHEEL
is_lib-1.0.0.dist-info/top_level.txt
is_lib-1.0.0.dist-info/RECORD
